geoalchemy2_mssql/__init__.py
geoalchemy2_mssql/_functions.py
geoalchemy2_mssql/alembic_helpers.py
geoalchemy2_mssql/comparator.py
geoalchemy2_mssql/elements.py
geoalchemy2_mssql/exc.py
geoalchemy2_mssql/functions.py
geoalchemy2_mssql/geo_types.py
geoalchemy2_mssql/py.typed
geoalchemy2_mssql/shape.py
geoalchemy2_mssql-0.0.3.dist-info/LICENSE.md
geoalchemy2_mssql-0.0.3.dist-info/WHEEL
geoalchemy2_mssql-0.0.3.dist-info/METADATA
geoalchemy2_mssql-0.0.3.dist-info/RECORD
