Metadata-Version: 2.1
Name: geoalchemy2_mssql
Version: 0.0.3
Summary: GeoAlchemy2 support for Microsoft SQL Server
Author-email: Wouter Kayser <wouter.kayser@wintor.com>
Requires-Python: >=3.10
Classifier: License :: OSI Approved :: MIT License
Classifier: Programming Language :: Python :: 3.10
Classifier: Programming Language :: Python :: 3.11
Classifier: Programming Language :: Python :: 3.12
Classifier: Operating System :: OS Independent
Requires-Dist: sqlalchemy
Requires-Dist: alembic ; extra == "dev"
Provides-Extra: dev
